jumpstarter_driver_dutlink/__init__.py
jumpstarter_driver_dutlink/conftest.py
jumpstarter_driver_dutlink/driver.py
jumpstarter_driver_dutlink/driver_test.py
jumpstarter_driver_dutlink/py.typed
jumpstarter_driver_dutlink-0.7.4.dist-info/METADATA
jumpstarter_driver_dutlink-0.7.4.dist-info/WHEEL
jumpstarter_driver_dutlink-0.7.4.dist-info/entry_points.txt
jumpstarter_driver_dutlink-0.7.4.dist-info/RECORD
