Metadata-Version: 2.4
Name: jumpstarter-driver-dutlink
Version: 0.7.4
Project-URL: Homepage, https://jumpstarter.dev
Project-URL: source_archive, https://github.com/jumpstarter-dev/repo/archive/c5d38de69eadbb8eb0388bcfe3430a679fff0059.zip
Author-email: Miguel Angel Ajo Pelayo <majopela@redhat.com>, Nick Cao <ncao@redhat.com>, Kirk Brauer <kbrauer@hatci.com>
License-Expression: Apache-2.0
Requires-Python: >=3.11
Requires-Dist: click>=8.1.7.2
Requires-Dist: jumpstarter-driver-composite==0.7.4
Requires-Dist: jumpstarter-driver-network==0.7.4
Requires-Dist: jumpstarter-driver-opendal==0.7.4
Requires-Dist: jumpstarter-driver-power==0.7.4
Requires-Dist: jumpstarter-driver-pyserial==0.7.4
Requires-Dist: jumpstarter==0.7.4
Requires-Dist: pyudev>=0.24.3
Requires-Dist: pyusb>=1.2.1
